Metadata-Version: 1.1
Name: TemplateRex
Version: 1.2
Summary: KISS Pure Logicless Template Engine
Home-page: https://github.com/troxel/TemplateRex-Python
Author: Steve Troxel
Author-email: troxel@perlworks.com
License: MIT
Keywords: template web html text logicless
Platform: UNKNOWN
Classifier: Environment :: Web Environment
Classifier: Intended Audience :: Developers
Classifier: License :: OSI Approved :: BSD License
Classifier: Operating System :: OS Independent
Classifier: Programming Language :: Python
Classifier: Programming Language :: Python :: 2.7
Classifier: Programming Language :: Python :: 3.5
Classifier: Programming Language :: Python :: 3.6
Classifier: Programming Language :: Python :: 3.7
Classifier: Topic :: Internet :: WWW/HTTP :: Dynamic Content
Classifier: Topic :: Software Development :: Libraries :: Python Modules
Classifier: Topic :: Text Processing :: Markup :: HTML
